pyobject/__init__.py
pyobject/browser.py
pyobject/code.py
pyobject/pyobj_extension.c
pyobject/pyobj_extension.cp310-win32.pyd
pyobject/search.py
pyobject/images/back.gif
pyobject/images/codeobject.gif
pyobject/images/dict.gif
pyobject/images/empty_dict.gif
pyobject/images/empty_list.gif
pyobject/images/empty_tuple.gif
pyobject/images/forward.gif
pyobject/images/function.gif
pyobject/images/list.gif
pyobject/images/number.gif
pyobject/images/python.gif
pyobject/images/python.ico
pyobject/images/refresh.gif
pyobject/images/string.gif
pyobject/images/tuple.gif
pyobject/objproxy/__init__.py
pyobject/objproxy/builtin_hook.py
pyobject/objproxy/optimize.py
pyobject/objproxy/utils.py
pyobject/tests/test_code.py
pyobject/tests/test_objproxy.py
pyobject/tests/test_objproxy_perf.py
pyobject-1.3.4.dist-info/LICENSE
pyobject-1.3.4.dist-info/METADATA
pyobject-1.3.4.dist-info/WHEEL
pyobject-1.3.4.dist-info/top_level.txt
pyobject-1.3.4.dist-info/RECORD
