Metadata-Version: 2.1
Name: pyobject
Version: 1.3.4
Summary: A multifunctional all-in-one utility tool for managing internal Python objects, compatible with nearly all Python 3 versions. 
Home-page: https://github.com/ekcbw/pyobject
Author: ekcbw
Author-email: u81430728@163.com
License: UNKNOWN
Keywords: pyobject,python,object,utility,object browser,bytecode,reflect,object search,OOP,reverse,对象,字节码,逆向
Platform: UNKNOWN
Classifier: Programming Language :: Python
Classifier: Topic :: Utilities
Classifier: Topic :: Software Development :: Bug Tracking
Classifier: Topic :: Software Development :: Debuggers
Classifier: Topic :: Software Development :: Object Brokering
Classifier: Topic :: Software Development :: Testing
Classifier: Topic :: Software Development :: Libraries :: Python Modules
License-File: LICENSE
Requires-Dist: astor; python_version <= "3.8"
